HISTORY.txt
MANIFEST.in
README.txt
setup.py
src/slc/__init__.py
src/slc.clicktracker.egg-info/PKG-INFO
src/slc.clicktracker.egg-info/SOURCES.txt
src/slc.clicktracker.egg-info/dependency_links.txt
src/slc.clicktracker.egg-info/entry_points.txt
src/slc.clicktracker.egg-info/namespace_packages.txt
src/slc.clicktracker.egg-info/not-zip-safe
src/slc.clicktracker.egg-info/requires.txt
src/slc.clicktracker.egg-info/top_level.txt
src/slc/clicktracker/__init__.py
src/slc/clicktracker/configure.zcml
src/slc/clicktracker/interfaces.py
src/slc/clicktracker/setuphandlers.py
src/slc/clicktracker/storage.py
src/slc/clicktracker/util.py
src/slc/clicktracker/browser/__init__.py
src/slc/clicktracker/browser/configure.zcml
src/slc/clicktracker/browser/tracker.pt
src/slc/clicktracker/browser/trackingsetup.pt
src/slc/clicktracker/browser/viewlets.py
src/slc/clicktracker/browser/views.py
src/slc/clicktracker/profiles/database/import_steps.xml
src/slc/clicktracker/profiles/database/metadata.xml
src/slc/clicktracker/profiles/database/slc.clicktracker-marker.txt
src/slc/clicktracker/profiles/default/actions.xml
src/slc/clicktracker/profiles/default/browserlayer.xml
src/slc/clicktracker/profiles/default/controlpanel.xml
src/slc/clicktracker/profiles/default/metadata.xml
src/slc/clicktracker/profiles/default/registry.xml
src/slc/clicktracker/sql/db.sql