Metadata-Version: 1.1
Name: slc.clicktracker
Version: 0.4
Summary: Track user movements on your plone site.
Home-page: https://github.com/syslabcom/slc.clicktracker
Author: Izak Burger, Syslab.com GmbH
Author-email: isburger@gmail.com
License: GPL
Keywords: CMFEditions flexbox
Platform: UNKNOWN
Classifier: Programming Language :: Python
Classifier: Programming Language :: Python
Classifier: Programming Language :: Python :: 2.6
Classifier: Programming Language :: Python :: 2.7
Classifier: Framework :: Plone
